aidub_frontend/__init__.py
aidub_frontend/dist/ai_dub.ico
aidub_frontend/dist/favicon.ico
aidub_frontend/dist/index.html
aidub_frontend/dist/novel_dub.ico
aidub_frontend/dist/assets/index-CmkypsQp.css
aidub_frontend/dist/assets/index-DBoLz-ZW.js
aidub_frontend-0.1.1.dist-info/METADATA
aidub_frontend-0.1.1.dist-info/WHEEL
aidub_frontend-0.1.1.dist-info/top_level.txt
aidub_frontend-0.1.1.dist-info/RECORD
