Metadata-Version: 2.4
Name: aidub-frontend
Version: 0.1.1
Summary: AI配音前端
Home-page: https://aidub.pro
Author: CyberWon
Author-email: mail@aidub.pro
Classifier: Programming Language :: Python :: 3
Classifier: License :: OSI Approved :: MIT License
Classifier: Operating System :: OS Independent
Dynamic: author
Dynamic: author-email
Dynamic: classifier
Dynamic: description
Dynamic: description-content-type
Dynamic: home-page
Dynamic: summary
